dil_gcm_envelope/__init__.py
dil_gcm_envelope/_version.py
dil_gcm_envelope/cli.py
dil_gcm_envelope/core.py
dil_gcm_envelope-0.1.1.dist-info/licenses/LICENSE
dil_gcm_envelope-0.1.1.dist-info/METADATA
dil_gcm_envelope-0.1.1.dist-info/WHEEL
dil_gcm_envelope-0.1.1.dist-info/top_level.txt
dil_gcm_envelope-0.1.1.dist-info/RECORD
