Metadata-Version: 2.4
Name: dil-gcm-envelope
Version: 0.1.1
Summary: AES-256-GCM envelope encryption (payload, iv, tag) compatible cross-language.
Author: Dev Innovations Labs
License: MIT
Keywords: aes-gcm,encryption,envelope,cryptography
Classifier: Programming Language :: Python :: 3
Classifier: License :: OSI Approved :: MIT License
Classifier: Operating System :: OS Independent
Requires-Python: >=3.8
License-File: LICENSE
Requires-Dist: cryptography>=39.0
Dynamic: license-file
